pdb2af/__init__.py
pdb2af/pdb2af.py
pdb2af/json/__init__.py
pdb2af-0.0.20.dist-info/LICENSE
pdb2af-0.0.20.dist-info/METADATA
pdb2af-0.0.20.dist-info/WHEEL
pdb2af-0.0.20.dist-info/entry_points.txt
pdb2af-0.0.20.dist-info/top_level.txt
pdb2af-0.0.20.dist-info/RECORD
