Metadata-Version: 2.1
Name: pdb2af
Version: 0.0.20
Summary: pdb2af downloads AF2 predictions that overlap with PDB structures
Home-page: https://github.com/nickjf/pdb2af
Author: Nick J Fowler
Author-email: nickjfowler0@gmail.com
Project-URL: Bug Tracker, https://github.com/nickjf/pdb2af/issues
Classifier: Programming Language :: Python :: 3
Classifier: License :: OSI Approved :: MIT License
Classifier: Operating System :: OS Independent
Requires-Python: >=3.6
License-File: LICENSE
Requires-Dist: pdb-tools
